pdf_server.py
mcp_pdf_reader-0.1.7.dist-info/METADATA
mcp_pdf_reader-0.1.7.dist-info/WHEEL
mcp_pdf_reader-0.1.7.dist-info/entry_points.txt
mcp_pdf_reader-0.1.7.dist-info/top_level.txt
mcp_pdf_reader-0.1.7.dist-info/RECORD
