Metadata-Version: 2.4
Name: mcp-pdf-reader
Version: 0.1.7
Summary: A PDF file reading server based on FastMCP. Supports PDF text extraction, OCR recognition, and image extraction via the MCP protocol, with a built-in web debugger for easy testing.
Requires-Python: >=3.10
Requires-Dist: fastmcp>=2.10.5
Requires-Dist: pymupdf>=1.26.3
